quantumvitas/__init__.py
quantumvitas-0.0.1.dist-info/METADATA
quantumvitas-0.0.1.dist-info/WHEEL
quantumvitas-0.0.1.dist-info/top_level.txt
quantumvitas-0.0.1.dist-info/RECORD
