Metadata-Version: 2.4
Name: quantumvitas
Version: 0.0.1
Summary: Placeholder package for QuantumVITAS (legacy GUI project).
Author: QMatSuite Developers
Requires-Python: >=3.8
